traintool/__init__.py
traintool/_version.txt
traintool/main.py
traintool/model_wrapper.py
traintool/utils.py
traintool/image_classification/__init__.py
traintool/image_classification/data_utils.py
traintool/image_classification/sklearn_models.py
traintool/image_classification/torch_models.py
traintool-0.0.3.dist-info/LICENSE
traintool-0.0.3.dist-info/METADATA
traintool-0.0.3.dist-info/WHEEL
traintool-0.0.3.dist-info/top_level.txt
traintool-0.0.3.dist-info/RECORD
