Metadata-Version: 2.1
Name: traintool
Version: 0.0.3
Summary: Machine learning in one line of code
Home-page: https://github.com/jrieke/traintool
Author: Johannes Rieke
Author-email: johannes.rieke@gmail.com
License: Apache-2.0 License
Platform: UNKNOWN
Classifier: Programming Language :: Python :: 3
Classifier: Programming Language :: Python :: 3.6
Classifier: Programming Language :: Python :: 3.7
Classifier: Programming Language :: Python :: 3.8
Classifier: Operating System :: OS Independent
Classifier: Development Status :: 2 - Pre-Alpha
Classifier: Intended Audience :: Developers
Requires-Python: >=3.6
Requires-Dist: numpy
Requires-Dist: torch
Requires-Dist: torchvision
Requires-Dist: pytorch-ignite
Requires-Dist: comet-ml
Requires-Dist: pyyaml (>=5.1)
Requires-Dist: scikit-learn
Requires-Dist: fastapi
Requires-Dist: uvicorn
Requires-Dist: joblib
Requires-Dist: tensorboardX
Requires-Dist: tensorboard
Requires-Dist: imageio
Requires-Dist: loguru
Requires-Dist: editdistance
